kivia/DB.py
kivia/app.py
kivia/bashrc.sh
kivia/ke.so
kivia/lolcat.py
kivia/spix.py
kivia/utils.py
kivia-1.1.6.1.dist-info/LICENSE
kivia-1.1.6.1.dist-info/METADATA
kivia-1.1.6.1.dist-info/WHEEL
kivia-1.1.6.1.dist-info/entry_points.txt
kivia-1.1.6.1.dist-info/top_level.txt
kivia-1.1.6.1.dist-info/RECORD
