Metadata-Version: 2.1
Name: kivia
Version: 1.1.6.1
Summary: A python cli which solves every problem in cli.
Home-page: https://github.com/wisdomrider/kivia-cli
Author: wisdomrider
Author-email: avishekzone@gmail.com
License: MIT
Platform: UNKNOWN
Classifier: License :: OSI Approved :: MIT License
Classifier: Programming Language :: Python :: 3.7
Requires-Dist: click
Requires-Dist: colorama
Requires-Dist: pycrypto
Requires-Dist: requests
Requires-Dist: sqliteclosedhelper
